pds_doi_core/__init__.py
pds_doi_core/actions/__init__.py
pds_doi_core/actions/action.py
pds_doi_core/actions/check.py
pds_doi_core/actions/draft.py
pds_doi_core/actions/list.py
pds_doi_core/actions/release.py
pds_doi_core/actions/reserve.py
pds_doi_core/actions/test/__init__.py
pds_doi_core/actions/test/check_test.py
pds_doi_core/actions/test/draft_test.py
pds_doi_core/actions/test/list_test.py
pds_doi_core/actions/test/release_test.py
pds_doi_core/actions/test/reserve_test.py
pds_doi_core/cmd/__init__.py
pds_doi_core/cmd/pds_doi_cmd.py
pds_doi_core/db/__init__.py
pds_doi_core/db/doi_database.py
pds_doi_core/entities/__init__.py
pds_doi_core/entities/doi.py
pds_doi_core/input/__init__.py
pds_doi_core/input/exceptions.py
pds_doi_core/input/input_util.py
pds_doi_core/input/node_util.py
pds_doi_core/input/osti_input_validator.py
pds_doi_core/input/pds4_util.py
pds_doi_core/input/test/__init__.py
pds_doi_core/input/test/input_util_test.py
pds_doi_core/input/test/read_bundle.py
pds_doi_core/input/test/read_remote_bundle.py
pds_doi_core/input/test/read_xls.py
pds_doi_core/outputs/__init__.py
pds_doi_core/outputs/osti.py
pds_doi_core/outputs/osti_release.py
pds_doi_core/outputs/osti_web_client.py
pds_doi_core/outputs/osti_web_parser.py
pds_doi_core/outputs/output_util.py
pds_doi_core/outputs/transaction.py
pds_doi_core/outputs/transaction_builder.py
pds_doi_core/outputs/transaction_logger.py
pds_doi_core/outputs/transaction_on_disk.py
pds_doi_core/outputs/test/__init__.py
pds_doi_core/outputs/test/send_osti_doi_test.py
pds_doi_core/references/__init__.py
pds_doi_core/references/contributors.py
pds_doi_core/references/test/__init__.py
pds_doi_core/references/test/contributors_test.py
pds_doi_core/util/__init__.py
pds_doi_core/util/cmd_parser.py
pds_doi_core/util/config_parser.py
pds_doi_core/util/doi_validator.py
pds_doi_core/util/doi_xml_differ.py
pds_doi_core/util/emailer.py
pds_doi_core/util/general_util.py
pds_doi_core/util/initialize_production_deployment.py
pds_doi_core-1.0.0.dist-info/LICENSE.txt
pds_doi_core-1.0.0.dist-info/METADATA
pds_doi_core-1.0.0.dist-info/NOTICE.txt
pds_doi_core-1.0.0.dist-info/WHEEL
pds_doi_core-1.0.0.dist-info/entry_points.txt
pds_doi_core-1.0.0.dist-info/top_level.txt
pds_doi_core-1.0.0.dist-info/RECORD
