Metadata-Version: 2.1
Name: pds-doi-core
Version: 1.0.0
Summary: short description of my pds module, less than 100-120 characters
Home-page: https://github.com/NASA-PDS/pds-template-python
Author: pds 
Author-email: pds_operator@jpl.nasa.gov
License: apache-2.0
Download-URL: https://github.com/NASA-PDS/pds-template-python/releases/download/....
Keywords: pds,doi,osti,dataCite
Platform: UNKNOWN
Classifier: Programming Language :: Python :: 3
Classifier: License :: OSI Approved :: Apache Software License
Classifier: Operating System :: OS Independent
Requires-Python: >=3.6
Requires-Dist: appdirs (>=1.4)
Requires-Dist: beautifulsoup4 (==4.8.2)
Requires-Dist: bs4 (==0.0.1)
Requires-Dist: certifi (==2020.4.5.1)
Requires-Dist: chardet (==3.0.4)
Requires-Dist: distlib (==0.3.1)
Requires-Dist: filelock (==3.0.12)
Requires-Dist: idna (==2.9)
Requires-Dist: importlib-metadata (==1.5.0)
Requires-Dist: importlib-resources (==3.0.0)
Requires-Dist: lxml (>=4.5)
Requires-Dist: nltk (==3.5)
Requires-Dist: numpy (>=1.18)
Requires-Dist: pandas (>=1.0)
Requires-Dist: pystache (>=0.5)
Requires-Dist: python-dateutil (>=2.8)
Requires-Dist: pytz (==2020.1)
Requires-Dist: requests (>=2.23)
Requires-Dist: six (>=1.14)
Requires-Dist: soupsieve (>=2.0)
Requires-Dist: urllib3 (>=1.25)
Requires-Dist: xlrd (>=1.2)
Requires-Dist: xmltodict (>=0.12)
Requires-Dist: zipp (>=3.1)
